mlbcal/__init__.py
mlbcal/main.py
mlbcal/data/__init__.py
mlbcal/data/teams.json
mlbcal/utils/__init__.py
mlbcal/utils/download_teams.py
mlbcal/utils/load.py
mlbcal-0.0.3.dist-info/LICENSE
mlbcal-0.0.3.dist-info/METADATA
mlbcal-0.0.3.dist-info/WHEEL
mlbcal-0.0.3.dist-info/entry_points.txt
mlbcal-0.0.3.dist-info/top_level.txt
mlbcal-0.0.3.dist-info/RECORD
