Metadata-Version: 2.1
Name: mlbcal
Version: 0.0.3
Summary: Download MLB game calendar for a given team
Home-page: https://github.com/joeeoj/mlbcal
Author: Mike Yu
Author-email: mike@mike-yu.com
License: MIT License
Platform: UNKNOWN
Classifier: Programming Language :: Python :: 3
Classifier: License :: OSI Approved :: MIT License
Classifier: Operating System :: OS Independent
Requires-Python: >=3.7
License-File: LICENSE
